[
  {
    "title": "The Sad Story Of Glynn",
    "video_url": "https://www.youtube.com/embed/CS197bQnAmE",
    "author_name": "Mainland Studios",
    "author_url": "https://www.youtube.com/@MainlandStudios",
    "cover": "https://img.youtube.com/vi/CS197bQnAmE/maxresdefault.jpg"
  },
  {
   "title": "Thomas' Odyssey",
   "video_url": "https://www.youtube.com/watch?v=tnJXtiSDMbM",
   "author_name": "The Unlucky Tug",
   "author_url": "https://www.youtube.com/@TheUnluckyTug_official",
   "cover": "https://img.youtube.com/vi/tnJXtiSDMbM/maxresdefault.jpg"
  },
  {
   "title": "Thomas & Friends: Season 14 & Misty Island Rescue (2010) in Retrospect — The Thomas Retrospective",
   "video_url": "https://www.youtube.com/watch?v=bHtPvuPK9wI",
   "author_name": "The Unlucky Tug",
   "author_url": "https://www.youtube.com/@TheUnluckyTug_official",
   "cover": "https://img.youtube.com/vi/bHtPvuPK9wI/maxresdefault.jpg"
  }
]
